LICENSE
MANIFEST.in
README.md
setup.py
ft232/__init__.py
ft232/d2xx.py
ft232/libftdi.py
pyft232.egg-info/PKG-INFO
pyft232.egg-info/SOURCES.txt
pyft232.egg-info/dependency_links.txt
pyft232.egg-info/requires.txt
pyft232.egg-info/top_level.txt