Metadata-Version: 1.0
Name: pyft232
Version: 0.7
Summary: Python bindings to d2xx and libftdi to access FT232 chips with the same interface as pyserial. Using this method gives easy access to the additional features on the chip like CBUS GPIO.
Home-page: UNKNOWN
Author: Logan Gunthorpe
Author-email: logang@deltatee.com
License: UNKNOWN
Platform: UNKNOWN
